Language_Translator/__init__.py
Language_Translator/main.py
Language_Translator-0.0.2.dist-info/LICENSE.txt
Language_Translator-0.0.2.dist-info/METADATA
Language_Translator-0.0.2.dist-info/WHEEL
Language_Translator-0.0.2.dist-info/top_level.txt
Language_Translator-0.0.2.dist-info/RECORD
