Metadata-Version: 2.1
Name: Language-Translator
Version: 0.0.2
Summary: Converting native languages to English
Home-page: https://github.com/Nagababu91768/Language-Translator
Author: Upputuri Nagababu
Author-email: nagababuuupputuri@gmail.com
License: MIT  # Example license
Platform: UNKNOWN
Classifier: Intended Audience :: Developers
Classifier: License :: OSI Approved :: MIT License
Classifier: Operating System :: OS Independent
Classifier: Programming Language :: Python :: 3.9
Classifier: Programming Language :: Python :: 3.6
Classifier: Programming Language :: Python :: 3.7
Classifier: Programming Language :: Python :: 3.8
Classifier: Topic :: Internet :: WWW/HTTP
Classifier: Topic :: Internet :: WWW/HTTP :: Dynamic Content
Requires-Python: >=3.6
License-File: LICENSE.txt
